tf_reader.py
tf_reader-0.2.dist-info/METADATA
tf_reader-0.2.dist-info/WHEEL
tf_reader-0.2.dist-info/top_level.txt
tf_reader-0.2.dist-info/RECORD
